[1,["09xSohe9FLQ45DJplw3T9f@6c48a"],["_textureSource"],["cc.SpriteFrame"],0,[{"name":"33","rect":{"x":22,"y":29,"width":92,"height":142},"offset":{"x":5,"y":-14.5},"originalSize":{"width":126,"height":171},"rotated":false,"capInsets":[0,0,0,0],"vertices":{"rawPosition":[-46,-71,0,46,-71,0,-46,71,0,46,71,0],"indexes":[0,1,2,2,1,3],"uv":[22,142,114,142,22,0,114,0],"nuv":[0.1746031746031746,0,0.9047619047619048,0,0.1746031746031746,0.8304093567251462,0.9047619047619048,0.8304093567251462],"minPos":{"x":-46,"y":-71,"z":0},"maxPos":{"x":46,"y":71,"z":0}},"packable":true,"pixelsToUnit":100,"pivot":{"x":0.5,"y":0.5},"meshType":0}],[0],0,[0],[0],[0]]
